{
 "Week": "2024-09-30",
 "LastWeek": "",
 "X": 0.2240515272881436,
 "Programs": [
  {
   "Program": "cmd/asm",
   "Version": "go1.23.1",
   "GoVersion": "go1.23.1",
   "GOOS": "linux",
   "GOARCH": "amd64",
   "Counters": {
    "asm/flag:D": 86,
    "asm/flag:I": 86,
    "asm/flag:gensymabis": 34,
    "asm/flag:o": 86,
    "asm/flag:p": 86,
    "asm/flag:trimpath": 86,
    "asm/invocations": 86
   },
   "Stacks": {}
  },
  {
   "Program": "cmd/cgo",
   "Version": "go1.23.1",
   "GoVersion": "go1.23.1",
   "GOOS": "linux",
   "GOARCH": "amd64",
   "Counters": {
    "cgo/flag:dynimport": 7,
    "cgo/flag:dynlinker": 1,
    "cgo/flag:dynout": 7,
    "cgo/flag:dynpackage": 7,
    "cgo/flag:import_runtime_cgo": 1,
    "cgo/flag:import_syscall": 1,
    "cgo/flag:importpath": 9,
    "cgo/flag:ldflags": 9,
    "cgo/flag:objdir": 9,
    "cgo/invocations": 16
   },
   "Stacks": {}
  },
  {
   "Program": "cmd/compile",
   "Version": "go1.23.1",
   "GoVersion": "go1.23.1",
   "GOOS": "linux",
   "GOARCH": "amd64",
   "Counters": {
    "compile/flag:asmhdr": 34,
    "compile/flag:buildid": 590,
    "compile/flag:c": 590,
    "compile/flag:complete": 543,
    "compile/flag:embedcfg": 38,
    "compile/flag:goversion": 590,
    "compile/flag:importcfg": 590,
    "compile/flag:lang": 590,
    "compile/flag:nolocalimports": 590,
    "compile/flag:o": 590,
    "compile/flag:p": 590,
    "compile/flag:pack": 590,
    "compile/flag:std": 225,
    "compile/flag:symabis": 34,
    "compile/flag:trimpath": 590,
    "compile/invocations": 622
   },
   "Stacks": {}
  },
  {
   "Program": "cmd/go",
   "Version": "go1.23.1",
   "GoVersion": "go1.23.1",
   "GOOS": "linux",
   "GOARCH": "amd64",
   "Counters": {
    "go/buildcache/hit": 420,
    "go/buildcache/miss": 594,
    "go/buildcache/stdlib-recompiled": 4,
    "go/goroot:usr-lib-go": 6,
    "go/install/flag:v": 6,
    "go/invocations": 6,
    "go/mode:module": 6,
    "go/platform/host/linux/major-version:6": 6,
    "go/platform/host/linux/version:6-10": 6,
    "go/platform/target/goamd64:v1": 6,
    "go/platform/target/goarch:amd64": 6,
    "go/platform/target/goos:linux": 6,
    "go/subcommand:install": 6
   },
   "Stacks": {}
  },
  {
   "Program": "cmd/link",
   "Version": "go1.23.1",
   "GoVersion": "go1.23.1",
   "GOOS": "linux",
   "GOARCH": "amd64",
   "Counters": {
    "link/flag:X": 2,
    "link/flag:buildid": 2,
    "link/flag:buildmode": 2,
    "link/flag:extld": 2,
    "link/flag:importcfg": 2,
    "link/flag:o": 2,
    "link/invocations": 4
   },
   "Stacks": {}
  }
 ],
 "Config": "v0.0.0-0"
}